{
  "ROW (basic) [FML]": {
    "prefix": ["<ROW"],
    "body": ["<ROW flex=\"1\" halign=\"between\" valign=\"center\">\n    ${0}\n</ROW>"],
    "description": "A simple flex based Row snippet with a common alignment"
  },
  "ROW (centered) [FML]": {
    "prefix": ["<ROW"],
    "body": ["<ROW width=\"${1:100%}\" height=\"${2:100%}\" center=\"true\">\n    ${0}\n</ROW>"],
    "description": "A sized Row snippet with its children centered on both axis"
  },
  "ROW (w/ alignments) [FML]": {
      "prefix": ["<ROW"],
      "body": ["<ROW halign=\"${2|start,end,center,between,around,evenly|}\" valign=\"${1|start,end,center|}\">\n    ${0}\n</ROW>"],
      "description": "A horizontally expanding Row snippet with separately aligned children on each axis"
  },
  "ROW (decorated) [FML]": {
    "prefix": ["<ROW"],
    "body": ["<ROW color=\"random,random\" radius=\"8\" border=\"all\" bordercolor=\"random\" borderwidth=\"2\" elevation=\"4\" shadowcolor=\"random\" shadowx=\"0\" shadowy=\"0\">\n    ${0}\n</ROW>"],
    "description": "A vertically expanding Row snippet with decoration attributes"
  }
}